{"DataList": [{"type": "Point", "id": 1, "coordinates": [105, 150.75], "properties": {"globaltype": "visiblePoint"}}, {"type": "Point", "id": 2, "coordinates": [105, 166.5], "properties": {"globaltype": "visiblePoint"}}, {"type": "Point", "id": 3, "coordinates": [106.5, 181.5], "properties": {"globaltype": "visiblePoint"}}, {"type": "Point", "id": 4, "coordinates": [110.5, 198.5], "properties": {"globaltype": "visiblePoint"}}, {"type": "Point", "id": 5, "coordinates": [113.5, 214.25], "properties": {"globaltype": "visiblePoint"}}, {"type": "Point", "id": 6, "coordinates": [116.5, 230], "properties": {"globaltype": "visiblePoint"}}, {"type": "Point", "id": 7, "coordinates": [119.73152345727912, 238.99393559797107], "properties": {"globaltype": "visiblePoint"}}, {"type": "Point", "id": 8, "coordinates": [123.910745688244, 247.58779457950675], "properties": {"globaltype": "visiblePoint"}}, {"type": "Point", "id": 9, "coordinates": [129.91452907905506, 255.13540798509777], "properties": {"globaltype": "visiblePoint"}}, {"type": "Point", "id": 10, "coordinates": [136.8344817979841, 261.82713555468115], "properties": {"globaltype": "visiblePoint"}}, {"type": "Point", "id": 11, "coordinates": [144.20623926828208, 267.9896187756036], "properties": {"globaltype": "visiblePoint"}}, {"type": "Point", "id": 12, "coordinates": [152.54883089333933, 272.8283219181368], "properties": {"globaltype": "visiblePoint"}}, {"type": "Point", "id": 13, "coordinates": [160.33001992382023, 278.48978857576606], "properties": {"globaltype": "visiblePoint"}}, {"type": "Point", "id": 14, "coordinates": [167.93242335901866, 284.421971905693], "properties": {"globaltype": "visiblePoint"}}, {"type": "Point", "id": 15, "coordinates": [175.70027889361327, 290.1379410726588], "properties": {"globaltype": "visiblePoint"}}, {"type": "Point", "id": 16, "coordinates": [184.4073818093251, 293.6601262016456], "properties": {"globaltype": "visiblePoint"}}, {"type": "Point", "id": 17, "coordinates": [194, 294.25], "properties": {"globaltype": "visiblePoint"}}, {"type": "Point", "id": 18, "coordinates": [204.82588005346162, 293.235073744988], "properties": {"globaltype": "visiblePoint"}}, {"type": "Point", "id": 19, "coordinates": [214.82100433596193, 289.75315946683446], "properties": {"globaltype": "visiblePoint"}}, {"type": "Point", "id": 20, "coordinates": [223.45584281073724, 283.2147414703365], "properties": {"globaltype": "visiblePoint"}}, {"type": "Point", "id": 21, "coordinates": [231.8730762559955, 276.3893391410554], "properties": {"globaltype": "visiblePoint"}}, {"type": "Point", "id": 22, "coordinates": [241.13903280226785, 270.6997167003619], "properties": {"globaltype": "visiblePoint"}}, {"type": "Point", "id": 23, "coordinates": [249.65912580469717, 263.9849408443718], "properties": {"globaltype": "visiblePoint"}}, {"type": "Point", "id": 24, "coordinates": [257.92419171409125, 256.9196425669865], "properties": {"globaltype": "visiblePoint"}}, {"type": "Point", "id": 25, "coordinates": [263.72639465405405, 247.80758259963966], "properties": {"globaltype": "visiblePoint"}}, {"type": "Point", "id": 26, "coordinates": [269.16005211570257, 238.38924299944887], "properties": {"globaltype": "visiblePoint"}}, {"type": "Point", "id": 27, "coordinates": [271.8049159052829, 227.9479625209443], "properties": {"globaltype": "visiblePoint"}}, {"type": "Point", "id": 28, "coordinates": [273.75, 217.25], "properties": {"globaltype": "visiblePoint"}}, {"type": "Point", "id": 29, "coordinates": [275.55, 204.1], "properties": {"globaltype": "visiblePoint"}}, {"type": "Point", "id": 30, "coordinates": [277.1, 190.95], "properties": {"globaltype": "visiblePoint"}}, {"type": "Point", "id": 31, "coordinates": [278.65, 177.79999999999998], "properties": {"globaltype": "visiblePoint"}}, {"type": "Point", "id": 32, "coordinates": [280.2, 164.64999999999998], "properties": {"globaltype": "inVisiblePoint"}}, {"type": "Point", "id": 33, "coordinates": [281.75, 151.5], "properties": {"globaltype": "inVisiblePoint"}}, {"type": "Point", "id": 34, "coordinates": [116.625, 158], "properties": {"globaltype": "visiblePoint"}}, {"type": "Point", "id": 35, "coordinates": [119.875, 149.25], "properties": {"globaltype": "visiblePoint"}}, {"type": "Point", "id": 36, "coordinates": [129.875, 143.5], "properties": {"globaltype": "visiblePoint"}}, {"type": "Point", "id": 37, "coordinates": [139.875, 147.25], "properties": {"globaltype": "visiblePoint"}}, {"type": "Point", "id": 38, "coordinates": [150.625, 149.75], "properties": {"globaltype": "visiblePoint"}}, {"type": "Point", "id": 39, "coordinates": [124.125, 156], "properties": {"globaltype": "visiblePoint"}}, {"type": "Point", "id": 40, "coordinates": [132.375, 153.25], "properties": {"globaltype": "visiblePoint"}}, {"type": "Point", "id": 41, "coordinates": [139.875, 156.75], "properties": {"globaltype": "visiblePoint"}}, {"type": "Point", "id": 42, "coordinates": [148.375, 156.25], "properties": {"globaltype": "visiblePoint"}}, {"type": "Point", "id": 43, "coordinates": [203.875, 150.25], "properties": {"globaltype": "visiblePoint"}}, {"type": "Point", "id": 44, "coordinates": [215.125, 141.25], "properties": {"globaltype": "visiblePoint"}}, {"type": "Point", "id": 45, "coordinates": [230.625, 135.25], "properties": {"globaltype": "visiblePoint"}}, {"type": "Point", "id": 46, "coordinates": [245.625, 142.25], "properties": {"globaltype": "visiblePoint"}}, {"type": "Point", "id": 47, "coordinates": [255.125, 152.25], "properties": {"globaltype": "visiblePoint"}}, {"type": "Point", "id": 48, "coordinates": [207.375, 157], "properties": {"globaltype": "visiblePoint"}}, {"type": "Point", "id": 49, "coordinates": [219.875, 153], "properties": {"globaltype": "visiblePoint"}}, {"type": "Point", "id": 50, "coordinates": [233.125, 150.25], "properties": {"globaltype": "visiblePoint"}}, {"type": "Point", "id": 51, "coordinates": [243.375, 151.5], "properties": {"globaltype": "visiblePoint"}}, {"type": "Point", "id": 52, "coordinates": [131.75, 178.5], "properties": {"globaltype": "visiblePoint"}}, {"type": "Point", "id": 53, "coordinates": [139.75, 174.625], "properties": {"globaltype": "visiblePoint"}}, {"type": "Point", "id": 54, "coordinates": [150.125, 175.75], "properties": {"globaltype": "visiblePoint"}}, {"type": "Point", "id": 55, "coordinates": [158.25, 182.75], "properties": {"globaltype": "visiblePoint"}}, {"type": "Point", "id": 56, "coordinates": [148.625, 186], "properties": {"globaltype": "visiblePoint"}}, {"type": "Point", "id": 57, "coordinates": [138.5, 184.625], "properties": {"globaltype": "visiblePoint"}}, {"type": "Point", "id": 58, "coordinates": [145.125, 174.5], "properties": {"globaltype": "visiblePoint"}}, {"type": "Point", "id": 59, "coordinates": [143.125, 186.25], "properties": {"globaltype": "visiblePoint"}}, {"type": "Point", "id": 60, "coordinates": [147.875, 178.75], "properties": {"globaltype": "visiblePoint"}}, {"type": "Point", "id": 61, "coordinates": [145.25, 180.75], "properties": {"globaltype": "visiblePoint"}}, {"type": "Point", "id": 62, "coordinates": [209.75, 179.25], "properties": {"globaltype": "visiblePoint"}}, {"type": "Point", "id": 63, "coordinates": [217.125, 170.25], "properties": {"globaltype": "visiblePoint"}}, {"type": "Point", "id": 64, "coordinates": [230.875, 169.25], "properties": {"globaltype": "visiblePoint"}}, {"type": "Point", "id": 65, "coordinates": [240, 174], "properties": {"globaltype": "visiblePoint"}}, {"type": "Point", "id": 66, "coordinates": [232.375, 180.5], "properties": {"globaltype": "visiblePoint"}}, {"type": "Point", "id": 67, "coordinates": [220.875, 182.25], "properties": {"globaltype": "visiblePoint"}}, {"type": "Point", "id": 68, "coordinates": [223.375, 168.25], "properties": {"globaltype": "visiblePoint"}}, {"type": "Point", "id": 69, "coordinates": [227.125, 181.75], "properties": {"globaltype": "visiblePoint"}}, {"type": "Point", "id": 70, "coordinates": [223.875, 173], "properties": {"globaltype": "visiblePoint"}}, {"type": "Point", "id": 71, "coordinates": [224.5, 176.75], "properties": {"globaltype": "visiblePoint"}}, {"type": "Point", "id": 72, "coordinates": [182.875, 178.375], "properties": {"globaltype": "visiblePoint"}}, {"type": "Point", "id": 73, "coordinates": [183.125, 191.5], "properties": {"globaltype": "visiblePoint"}}, {"type": "Point", "id": 74, "coordinates": [183.625, 203.875], "properties": {"globaltype": "visiblePoint"}}, {"type": "Point", "id": 75, "coordinates": [183.875, 216], "properties": {"globaltype": "visiblePoint"}}, {"type": "Point", "id": 76, "coordinates": [173.625, 181.75], "properties": {"globaltype": "visiblePoint"}}, {"type": "Point", "id": 77, "coordinates": [193, 180.5], "properties": {"globaltype": "visiblePoint"}}, {"type": "Point", "id": 78, "coordinates": [170.625, 213.25], "properties": {"globaltype": "visiblePoint"}}, {"type": "Point", "id": 79, "coordinates": [198.875, 212], "properties": {"globaltype": "visiblePoint"}}, {"type": "Point", "id": 80, "coordinates": [162.75, 223], "properties": {"globaltype": "visiblePoint"}}, {"type": "Point", "id": 81, "coordinates": [209.75, 221.75], "properties": {"globaltype": "visiblePoint"}}, {"type": "Point", "id": 82, "coordinates": [169.625, 230.75], "properties": {"globaltype": "visiblePoint"}}, {"type": "Point", "id": 83, "coordinates": [179, 232.5], "properties": {"globaltype": "visiblePoint"}}, {"type": "Point", "id": 84, "coordinates": [187.625, 232.5], "properties": {"globaltype": "visiblePoint"}}, {"type": "Point", "id": 85, "coordinates": [197, 231.25], "properties": {"globaltype": "visiblePoint"}}, {"type": "Point", "id": 86, "coordinates": [204.375, 227.75], "properties": {"globaltype": "visiblePoint"}}, {"type": "Point", "id": 87, "coordinates": [167.75, 253.625], "properties": {"globaltype": "visiblePoint"}}, {"type": "Point", "id": 88, "coordinates": [183.75, 247.75], "properties": {"globaltype": "visiblePoint"}}, {"type": "Point", "id": 89, "coordinates": [189.5, 249.25], "properties": {"globaltype": "visiblePoint"}}, {"type": "Point", "id": 90, "coordinates": [195, 246.75], "properties": {"globaltype": "visiblePoint"}}, {"type": "Point", "id": 91, "coordinates": [216.5, 250.25], "properties": {"globaltype": "visiblePoint"}}, {"type": "Point", "id": 92, "coordinates": [190.75, 265.5], "properties": {"globaltype": "visiblePoint"}}, {"type": "Point", "id": 93, "coordinates": [176.25, 250.25], "properties": {"globaltype": "visiblePoint"}}, {"type": "Point", "id": 94, "coordinates": [207.25, 248], "properties": {"globaltype": "visiblePoint"}}, {"type": "Point", "id": 95, "coordinates": [207, 259], "properties": {"globaltype": "visiblePoint"}}, {"type": "Point", "id": 96, "coordinates": [177.25, 261.75], "properties": {"globaltype": "visiblePoint"}}, {"type": "Point", "id": 97, "coordinates": [169, 253.5], "properties": {"globaltype": "visiblePoint"}}, {"type": "Point", "id": 98, "coordinates": [215.375, 250.375], "properties": {"globaltype": "visiblePoint"}}, {"type": "Point", "id": 99, "coordinates": [184, 253.375], "properties": {"globaltype": "visiblePoint"}}, {"type": "Point", "id": 100, "coordinates": [190, 254.25], "properties": {"globaltype": "visiblePoint"}}, {"type": "Point", "id": 101, "coordinates": [195.25, 252.75], "properties": {"globaltype": "visiblePoint"}}, {"type": "Point", "id": 102, "coordinates": [184.125, 254.5], "properties": {"globaltype": "visiblePoint"}}, {"type": "Point", "id": 103, "coordinates": [190.125, 255.75], "properties": {"globaltype": "visiblePoint"}}, {"type": "Point", "id": 104, "coordinates": [195.375, 254.5], "properties": {"globaltype": "visiblePoint"}}, {"type": "Point", "id": 105, "coordinates": [184.5, 265.125], "properties": {"globaltype": "visiblePoint"}}, {"type": "Point", "id": 106, "coordinates": [196.375, 264.5], "properties": {"globaltype": "visiblePoint"}}], "WorkLoad": {"race": "Asian", "eye": "open", "orientation": "forward", "background": "outdoor", "gender": "female", "mouth": "close", "occlusion": "covered", "cap": "no", "age": "teenager", "glasses": "no"}, "Filepath": "session01\\000015.jpg"}