{"DataList": [{"type": "Point", "id": 1, "coordinates": [87.25, 146.5], "properties": {"globaltype": "visiblePoint"}}, {"type": "Point", "id": 2, "coordinates": [85.20779160454629, 158.4128823068133], "properties": {"globaltype": "visiblePoint"}}, {"type": "Point", "id": 3, "coordinates": [83.87311962145012, 170.406966435348], "properties": {"globaltype": "visiblePoint"}}, {"type": "Point", "id": 4, "coordinates": [83.45158340056273, 182.46147965407977], "properties": {"globaltype": "visiblePoint"}}, {"type": "Point", "id": 5, "coordinates": [85.10307333278949, 194.43478166272385], "properties": {"globaltype": "visiblePoint"}}, {"type": "Point", "id": 6, "coordinates": [85.75, 206.5], "properties": {"globaltype": "visiblePoint"}}, {"type": "Point", "id": 7, "coordinates": [86.8058279522813, 216.21361716098806], "properties": {"globaltype": "visiblePoint"}}, {"type": "Point", "id": 8, "coordinates": [88.53108632890087, 225.8255523477156], "properties": {"globaltype": "visiblePoint"}}, {"type": "Point", "id": 9, "coordinates": [91.6857802928074, 235.01255539951146], "properties": {"globaltype": "visiblePoint"}}, {"type": "Point", "id": 10, "coordinates": [96.49901790781037, 243.4305682463041], "properties": {"globaltype": "visiblePoint"}}, {"type": "Point", "id": 11, "coordinates": [102.62746693103173, 251.0169888048761], "properties": {"globaltype": "visiblePoint"}}, {"type": "Point", "id": 12, "coordinates": [110.60452586060389, 256.65929877945155], "properties": {"globaltype": "visiblePoint"}}, {"type": "Point", "id": 13, "coordinates": [119.01170964570647, 261.61761646983695], "properties": {"globaltype": "visiblePoint"}}, {"type": "Point", "id": 14, "coordinates": [127.53123789184205, 266.4007281716718], "properties": {"globaltype": "visiblePoint"}}, {"type": "Point", "id": 15, "coordinates": [135.95305111418693, 271.35473594952174], "properties": {"globaltype": "visiblePoint"}}, {"type": "Point", "id": 16, "coordinates": [144.47916937947136, 276], "properties": {"globaltype": "visiblePoint"}}, {"type": "Point", "id": 17, "coordinates": [154.25, 276], "properties": {"globaltype": "visiblePoint"}}, {"type": "Point", "id": 18, "coordinates": [163.97849959001485, 274.07129359412625], "properties": {"globaltype": "visiblePoint"}}, {"type": "Point", "id": 19, "coordinates": [173.19482725644406, 270.62206909742235], "properties": {"globaltype": "visiblePoint"}}, {"type": "Point", "id": 20, "coordinates": [182.16119056751145, 266.59712548799337], "properties": {"globaltype": "visiblePoint"}}, {"type": "Point", "id": 21, "coordinates": [190.67479891234822, 261.6437533600883], "properties": {"globaltype": "visiblePoint"}}, {"type": "Point", "id": 22, "coordinates": [198.6846782213373, 255.94652429968176], "properties": {"globaltype": "visiblePoint"}}, {"type": "Point", "id": 23, "coordinates": [206.44437575612918, 249.87985168157175], "properties": {"globaltype": "visiblePoint"}}, {"type": "Point", "id": 24, "coordinates": [212.9668743477135, 242.5242654732782], "properties": {"globaltype": "visiblePoint"}}, {"type": "Point", "id": 25, "coordinates": [217.6385932540439, 234.02859512117274], "properties": {"globaltype": "visiblePoint"}}, {"type": "Point", "id": 26, "coordinates": [220.51439760288946, 224.6386633339274], "properties": {"globaltype": "visiblePoint"}}, {"type": "Point", "id": 27, "coordinates": [222.25719880144473, 214.94433166696373], "properties": {"globaltype": "visiblePoint"}}, {"type": "Point", "id": 28, "coordinates": [224, 205.25], "properties": {"globaltype": "visiblePoint"}}, {"type": "Point", "id": 29, "coordinates": [225.3480180935981, 194.94052493348153], "properties": {"globaltype": "visiblePoint"}}, {"type": "Point", "id": 30, "coordinates": [226.20289502442012, 184.33120667277058], "properties": {"globaltype": "visiblePoint"}}, {"type": "Point", "id": 31, "coordinates": [226.9880409396073, 173.71503503341927], "properties": {"globaltype": "visiblePoint"}}, {"type": "Point", "id": 32, "coordinates": [227.25, 163], "properties": {"globaltype": "visiblePoint"}}, {"type": "Point", "id": 33, "coordinates": [227, 150.75], "properties": {"globaltype": "visiblePoint"}}, {"type": "Point", "id": 34, "coordinates": [94.25, 138.25], "properties": {"globaltype": "visiblePoint"}}, {"type": "Point", "id": 35, "coordinates": [103.375, 129.75], "properties": {"globaltype": "visiblePoint"}}, {"type": "Point", "id": 36, "coordinates": [115.375, 128.25], "properties": {"globaltype": "visiblePoint"}}, {"type": "Point", "id": 37, "coordinates": [128.875, 130.25], "properties": {"globaltype": "visiblePoint"}}, {"type": "Point", "id": 38, "coordinates": [139.875, 136.75], "properties": {"globaltype": "visiblePoint"}}, {"type": "Point", "id": 39, "coordinates": [105.125, 137.875], "properties": {"globaltype": "visiblePoint"}}, {"type": "Point", "id": 40, "coordinates": [115.25, 138], "properties": {"globaltype": "visiblePoint"}}, {"type": "Point", "id": 41, "coordinates": [126.125, 139.5], "properties": {"globaltype": "visiblePoint"}}, {"type": "Point", "id": 42, "coordinates": [136.125, 141.75], "properties": {"globaltype": "visiblePoint"}}, {"type": "Point", "id": 43, "coordinates": [172.375, 136.625], "properties": {"globaltype": "visiblePoint"}}, {"type": "Point", "id": 44, "coordinates": [184.25, 131.375], "properties": {"globaltype": "visiblePoint"}}, {"type": "Point", "id": 45, "coordinates": [196.375, 129.5], "properties": {"globaltype": "visiblePoint"}}, {"type": "Point", "id": 46, "coordinates": [207.875, 133.125], "properties": {"globaltype": "visiblePoint"}}, {"type": "Point", "id": 47, "coordinates": [215.875, 142.25], "properties": {"globaltype": "visiblePoint"}}, {"type": "Point", "id": 48, "coordinates": [177.375, 141.25], "properties": {"globaltype": "visiblePoint"}}, {"type": "Point", "id": 49, "coordinates": [186.625, 138.875], "properties": {"globaltype": "visiblePoint"}}, {"type": "Point", "id": 50, "coordinates": [197.375, 138.25], "properties": {"globaltype": "visiblePoint"}}, {"type": "Point", "id": 51, "coordinates": [207.125, 139.875], "properties": {"globaltype": "visiblePoint"}}, {"type": "Point", "id": 52, "coordinates": [111.625, 154.375], "properties": {"globaltype": "visiblePoint"}}, {"type": "Point", "id": 53, "coordinates": [117.5, 151.25], "properties": {"globaltype": "visiblePoint"}}, {"type": "Point", "id": 54, "coordinates": [125.25, 152.75], "properties": {"globaltype": "visiblePoint"}}, {"type": "Point", "id": 55, "coordinates": [130.375, 156.25], "properties": {"globaltype": "visiblePoint"}}, {"type": "Point", "id": 56, "coordinates": [125, 158.625], "properties": {"globaltype": "visiblePoint"}}, {"type": "Point", "id": 57, "coordinates": [116.875, 157.625], "properties": {"globaltype": "visiblePoint"}}, {"type": "Point", "id": 58, "coordinates": [121.625, 151], "properties": {"globaltype": "visiblePoint"}}, {"type": "Point", "id": 59, "coordinates": [120.375, 158.75], "properties": {"globaltype": "visiblePoint"}}, {"type": "Point", "id": 60, "coordinates": [121.125, 154.75], "properties": {"globaltype": "visiblePoint"}}, {"type": "Point", "id": 61, "coordinates": [120.875, 155.25], "properties": {"globaltype": "visiblePoint"}}, {"type": "Point", "id": 62, "coordinates": [179.75, 154.875], "properties": {"globaltype": "visiblePoint"}}, {"type": "Point", "id": 63, "coordinates": [185.125, 151.5], "properties": {"globaltype": "visiblePoint"}}, {"type": "Point", "id": 64, "coordinates": [192.5, 151.75], "properties": {"globaltype": "visiblePoint"}}, {"type": "Point", "id": 65, "coordinates": [197.625, 155.125], "properties": {"globaltype": "visiblePoint"}}, {"type": "Point", "id": 66, "coordinates": [192.625, 158.625], "properties": {"globaltype": "visiblePoint"}}, {"type": "Point", "id": 67, "coordinates": [184.875, 158.375], "properties": {"globaltype": "visiblePoint"}}, {"type": "Point", "id": 68, "coordinates": [188.75, 151], "properties": {"globaltype": "visiblePoint"}}, {"type": "Point", "id": 69, "coordinates": [188.75, 159], "properties": {"globaltype": "visiblePoint"}}, {"type": "Point", "id": 70, "coordinates": [189.125, 153.875], "properties": {"globaltype": "visiblePoint"}}, {"type": "Point", "id": 71, "coordinates": [188.75, 155.125], "properties": {"globaltype": "visiblePoint"}}, {"type": "Point", "id": 72, "coordinates": [154.125, 153.125], "properties": {"globaltype": "visiblePoint"}}, {"type": "Point", "id": 73, "coordinates": [153.04166666666666, 167.125], "properties": {"globaltype": "visiblePoint"}}, {"type": "Point", "id": 74, "coordinates": [152.08333333333334, 179.125], "properties": {"globaltype": "visiblePoint"}}, {"type": "Point", "id": 75, "coordinates": [151.125, 191.125], "properties": {"globaltype": "visiblePoint"}}, {"type": "Point", "id": 76, "coordinates": [149.25, 155.5], "properties": {"globaltype": "visiblePoint"}}, {"type": "Point", "id": 77, "coordinates": [159.125, 155.375], "properties": {"globaltype": "visiblePoint"}}, {"type": "Point", "id": 78, "coordinates": [140.375, 188.75], "properties": {"globaltype": "visiblePoint"}}, {"type": "Point", "id": 79, "coordinates": [165.625, 189.75], "properties": {"globaltype": "visiblePoint"}}, {"type": "Point", "id": 80, "coordinates": [132.875, 197], "properties": {"globaltype": "visiblePoint"}}, {"type": "Point", "id": 81, "coordinates": [173.625, 198.5], "properties": {"globaltype": "visiblePoint"}}, {"type": "Point", "id": 82, "coordinates": [140.75, 204.75], "properties": {"globaltype": "visiblePoint"}}, {"type": "Point", "id": 83, "coordinates": [146.875, 204.5], "properties": {"globaltype": "visiblePoint"}}, {"type": "Point", "id": 84, "coordinates": [152.75, 204.375], "properties": {"globaltype": "visiblePoint"}}, {"type": "Point", "id": 85, "coordinates": [159.25, 205.125], "properties": {"globaltype": "visiblePoint"}}, {"type": "Point", "id": 86, "coordinates": [165.375, 205.5], "properties": {"globaltype": "visiblePoint"}}, {"type": "Point", "id": 87, "coordinates": [127.5, 227.125], "properties": {"globaltype": "visiblePoint"}}, {"type": "Point", "id": 88, "coordinates": [147.375, 221.25], "properties": {"globaltype": "visiblePoint"}}, {"type": "Point", "id": 89, "coordinates": [151, 221.625], "properties": {"globaltype": "visiblePoint"}}, {"type": "Point", "id": 90, "coordinates": [155, 221.875], "properties": {"globaltype": "visiblePoint"}}, {"type": "Point", "id": 91, "coordinates": [175.25, 229.125], "properties": {"globaltype": "visiblePoint"}}, {"type": "Point", "id": 92, "coordinates": [152, 241.5], "properties": {"globaltype": "visiblePoint"}}, {"type": "Point", "id": 93, "coordinates": [137.625, 222.625], "properties": {"globaltype": "visiblePoint"}}, {"type": "Point", "id": 94, "coordinates": [165.625, 224.625], "properties": {"globaltype": "visiblePoint"}}, {"type": "Point", "id": 95, "coordinates": [163.625, 235.75], "properties": {"globaltype": "visiblePoint"}}, {"type": "Point", "id": 96, "coordinates": [138.5, 235.625], "properties": {"globaltype": "visiblePoint"}}, {"type": "Point", "id": 97, "coordinates": [128.25, 227.125], "properties": {"globaltype": "visiblePoint"}}, {"type": "Point", "id": 98, "coordinates": [174.625, 229], "properties": {"globaltype": "visiblePoint"}}, {"type": "Point", "id": 99, "coordinates": [147.375, 228.625], "properties": {"globaltype": "visiblePoint"}}, {"type": "Point", "id": 100, "coordinates": [151.5, 229], "properties": {"globaltype": "visiblePoint"}}, {"type": "Point", "id": 101, "coordinates": [155.125, 228.875], "properties": {"globaltype": "visiblePoint"}}, {"type": "Point", "id": 102, "coordinates": [147.5, 228.75], "properties": {"globaltype": "visiblePoint"}}, {"type": "Point", "id": 103, "coordinates": [151.375, 229], "properties": {"globaltype": "visiblePoint"}}, {"type": "Point", "id": 104, "coordinates": [155.25, 229.125], "properties": {"globaltype": "visiblePoint"}}, {"type": "Point", "id": 105, "coordinates": [147.625, 241.25], "properties": {"globaltype": "visiblePoint"}}, {"type": "Point", "id": 106, "coordinates": [156.25, 241.75], "properties": {"globaltype": "visiblePoint"}}], "WorkLoad": {"race": "Asian", "eye": "open", "orientation": "forward", "background": "nocolor", "gender": "female", "mouth": "close", "occlusion": "uncovered", "cap": "no", "age": "midlife", "glasses": "yes"}, "Filepath": "session01\\000292.jpg"}