{"DataList": [{"type": "Point", "id": 1, "coordinates": [70.75, 199.75], "properties": {"globaltype": "visiblePoint"}}, {"type": "Point", "id": 2, "coordinates": [69.5, 216.72497979525025], "properties": {"globaltype": "visiblePoint"}}, {"type": "Point", "id": 3, "coordinates": [71.07935111441789, 231.84513335813415], "properties": {"globaltype": "visiblePoint"}}, {"type": "Point", "id": 4, "coordinates": [73.20321874972122, 246.92023214110475], "properties": {"globaltype": "visiblePoint"}}, {"type": "Point", "id": 5, "coordinates": [75.59529219224335, 261.95612235124395], "properties": {"globaltype": "visiblePoint"}}, {"type": "Point", "id": 6, "coordinates": [79.5, 277.25], "properties": {"globaltype": "visiblePoint"}}, {"type": "Point", "id": 7, "coordinates": [83.23317308964373, 290.74772271357426], "properties": {"globaltype": "visiblePoint"}}, {"type": "Point", "id": 8, "coordinates": [89.24176656420565, 302.8948504781384], "properties": {"globaltype": "visiblePoint"}}, {"type": "Point", "id": 9, "coordinates": [95.7332517330576, 314.839183188826], "properties": {"globaltype": "visiblePoint"}}, {"type": "Point", "id": 10, "coordinates": [104.14357194640895, 325.4859827685775], "properties": {"globaltype": "visiblePoint"}}, {"type": "Point", "id": 11, "coordinates": [113.7632142738999, 334.99452764024187], "properties": {"globaltype": "visiblePoint"}}, {"type": "Point", "id": 12, "coordinates": [124.37384746913085, 343.4886260441261], "properties": {"globaltype": "visiblePoint"}}, {"type": "Point", "id": 13, "coordinates": [135.8335844022422, 350.80167035774974], "properties": {"globaltype": "visiblePoint"}}, {"type": "Point", "id": 14, "coordinates": [147.3968681825965, 357.9498821492415], "properties": {"globaltype": "visiblePoint"}}, {"type": "Point", "id": 15, "coordinates": [159.64602503856256, 363.80475938946097], "properties": {"globaltype": "visiblePoint"}}, {"type": "Point", "id": 16, "coordinates": [172.49719126546026, 368.1660425034356], "properties": {"globaltype": "visiblePoint"}}, {"type": "Point", "id": 17, "coordinates": [186, 369], "properties": {"globaltype": "visiblePoint"}}, {"type": "Point", "id": 18, "coordinates": [198.85055524462098, 365.7885216106929], "properties": {"globaltype": "visiblePoint"}}, {"type": "Point", "id": 19, "coordinates": [211.23155663368632, 361.594956624074], "properties": {"globaltype": "visiblePoint"}}, {"type": "Point", "id": 20, "coordinates": [222.18662275340694, 354.5281669609306], "properties": {"globaltype": "visiblePoint"}}, {"type": "Point", "id": 21, "coordinates": [232.6698541451955, 346.7576276229539], "properties": {"globaltype": "visiblePoint"}}, {"type": "Point", "id": 22, "coordinates": [242.50747908895647, 338.1497057971631], "properties": {"globaltype": "visiblePoint"}}, {"type": "Point", "id": 23, "coordinates": [251.51345538631082, 328.7036126904003], "properties": {"globaltype": "visiblePoint"}}, {"type": "Point", "id": 24, "coordinates": [260.1979686307073, 318.93353529045424], "properties": {"globaltype": "visiblePoint"}}, {"type": "Point", "id": 25, "coordinates": [268.4506013832732, 308.85606895844074], "properties": {"globaltype": "visiblePoint"}}, {"type": "Point", "id": 26, "coordinates": [274.66872399542393, 297.37266616616637], "properties": {"globaltype": "visiblePoint"}}, {"type": "Point", "id": 27, "coordinates": [279.22019165686186, 285.11871476998726], "properties": {"globaltype": "visiblePoint"}}, {"type": "Point", "id": 28, "coordinates": [282.5, 272.5], "properties": {"globaltype": "visiblePoint"}}, {"type": "Point", "id": 29, "coordinates": [283.71822610230504, 257.18515757102244], "properties": {"globaltype": "visiblePoint"}}, {"type": "Point", "id": 30, "coordinates": [285.2512358427316, 241.901150997717], "properties": {"globaltype": "visiblePoint"}}, {"type": "Point", "id": 31, "coordinates": [287.02809900958795, 226.64103203530334], "properties": {"globaltype": "visiblePoint"}}, {"type": "Point", "id": 32, "coordinates": [288.5, 211.36321819999796], "properties": {"globaltype": "visiblePoint"}}, {"type": "Point", "id": 33, "coordinates": [288.5, 196], "properties": {"globaltype": "visiblePoint"}}, {"type": "Point", "id": 34, "coordinates": [79, 179.5], "properties": {"globaltype": "inVisiblePoint"}}, {"type": "Point", "id": 35, "coordinates": [94.5, 163.25], "properties": {"globaltype": "visiblePoint"}}, {"type": "Point", "id": 36, "coordinates": [113, 159], "properties": {"globaltype": "visiblePoint"}}, {"type": "Point", "id": 37, "coordinates": [132.25, 161.5], "properties": {"globaltype": "visiblePoint"}}, {"type": "Point", "id": 38, "coordinates": [150.75, 169.125], "properties": {"globaltype": "visiblePoint"}}, {"type": "Point", "id": 39, "coordinates": [95, 170.75], "properties": {"globaltype": "visiblePoint"}}, {"type": "Point", "id": 40, "coordinates": [113.5, 166.875], "properties": {"globaltype": "visiblePoint"}}, {"type": "Point", "id": 41, "coordinates": [130.375, 170.75], "properties": {"globaltype": "visiblePoint"}}, {"type": "Point", "id": 42, "coordinates": [147.5, 176.875], "properties": {"globaltype": "visiblePoint"}}, {"type": "Point", "id": 43, "coordinates": [197.625, 169.75], "properties": {"globaltype": "visiblePoint"}}, {"type": "Point", "id": 44, "coordinates": [213.25, 160.125], "properties": {"globaltype": "visiblePoint"}}, {"type": "Point", "id": 45, "coordinates": [228.875, 155.875], "properties": {"globaltype": "visiblePoint"}}, {"type": "Point", "id": 46, "coordinates": [247.375, 156.125], "properties": {"globaltype": "visiblePoint"}}, {"type": "Point", "id": 47, "coordinates": [263.25, 169.5], "properties": {"globaltype": "visiblePoint"}}, {"type": "Point", "id": 48, "coordinates": [206.125, 176], "properties": {"globaltype": "visiblePoint"}}, {"type": "Point", "id": 49, "coordinates": [219.75, 169.25], "properties": {"globaltype": "visiblePoint"}}, {"type": "Point", "id": 50, "coordinates": [234.75, 164], "properties": {"globaltype": "visiblePoint"}}, {"type": "Point", "id": 51, "coordinates": [249.625, 163.875], "properties": {"globaltype": "visiblePoint"}}, {"type": "Point", "id": 52, "coordinates": [102.23211669921875, 200.99999237060547], "properties": {"globaltype": "visiblePoint"}}, {"type": "Point", "id": 53, "coordinates": [115.10711669921875, 191.49999237060547], "properties": {"globaltype": "visiblePoint"}}, {"type": "Point", "id": 54, "coordinates": [133.60711669921875, 192.49999237060547], "properties": {"globaltype": "visiblePoint"}}, {"type": "Point", "id": 55, "coordinates": [144.73211669921875, 201.49999237060547], "properties": {"globaltype": "visiblePoint"}}, {"type": "Point", "id": 56, "coordinates": [131.875, 204.875], "properties": {"globaltype": "visiblePoint"}}, {"type": "Point", "id": 57, "coordinates": [116.48211669921875, 204.99999237060547], "properties": {"globaltype": "visiblePoint"}}, {"type": "Point", "id": 58, "coordinates": [124.60711669921875, 189.99999237060547], "properties": {"globaltype": "visiblePoint"}}, {"type": "Point", "id": 59, "coordinates": [124.10711669921875, 205.37499237060547], "properties": {"globaltype": "visiblePoint"}}, {"type": "Point", "id": 60, "coordinates": [125.48211669921875, 196.87499237060547], "properties": {"globaltype": "visiblePoint"}}, {"type": "Point", "id": 61, "coordinates": [123.48211669921875, 201.24999237060547], "properties": {"globaltype": "visiblePoint"}}, {"type": "Point", "id": 62, "coordinates": [207.85711669921875, 199.62499237060547], "properties": {"globaltype": "visiblePoint"}}, {"type": "Point", "id": 63, "coordinates": [221.125, 189.625], "properties": {"globaltype": "visiblePoint"}}, {"type": "Point", "id": 64, "coordinates": [239.10711669921875, 187.62499237060547], "properties": {"globaltype": "visiblePoint"}}, {"type": "Point", "id": 65, "coordinates": [251.98211669921875, 195.12499237060547], "properties": {"globaltype": "visiblePoint"}}, {"type": "Point", "id": 66, "coordinates": [240.35711669921875, 202.12499237060547], "properties": {"globaltype": "visiblePoint"}}, {"type": "Point", "id": 67, "coordinates": [224.35711669921875, 202.37499237060547], "properties": {"globaltype": "visiblePoint"}}, {"type": "Point", "id": 68, "coordinates": [230, 187.125], "properties": {"globaltype": "visiblePoint"}}, {"type": "Point", "id": 69, "coordinates": [231.85711669921875, 202.37499237060547], "properties": {"globaltype": "visiblePoint"}}, {"type": "Point", "id": 70, "coordinates": [231.23211669921875, 194.62499237060547], "properties": {"globaltype": "visiblePoint"}}, {"type": "Point", "id": 71, "coordinates": [230.35711669921875, 197.37499237060547], "properties": {"globaltype": "visiblePoint"}}, {"type": "Point", "id": 72, "coordinates": [177.1250495742188, 197.02272413476567], "properties": {"globaltype": "visiblePoint"}}, {"type": "Point", "id": 73, "coordinates": [177.23211669921875, 215.37499237060547], "properties": {"globaltype": "visiblePoint"}}, {"type": "Point", "id": 74, "coordinates": [177.23211669921875, 233.24999237060547], "properties": {"globaltype": "visiblePoint"}}, {"type": "Point", "id": 75, "coordinates": [177.625, 251.375], "properties": {"globaltype": "visiblePoint"}}, {"type": "Point", "id": 76, "coordinates": [166.98211669921875, 200.87499237060547], "properties": {"globaltype": "visiblePoint"}}, {"type": "Point", "id": 77, "coordinates": [188.60711669921875, 200.24999237060547], "properties": {"globaltype": "visiblePoint"}}, {"type": "Point", "id": 78, "coordinates": [162.875, 244.625], "properties": {"globaltype": "visiblePoint"}}, {"type": "Point", "id": 79, "coordinates": [193.625, 243.625], "properties": {"globaltype": "visiblePoint"}}, {"type": "Point", "id": 80, "coordinates": [149.375, 257.375], "properties": {"globaltype": "visiblePoint"}}, {"type": "Point", "id": 81, "coordinates": [209.125, 257.625], "properties": {"globaltype": "visiblePoint"}}, {"type": "Point", "id": 82, "coordinates": [158.875, 269.875], "properties": {"globaltype": "visiblePoint"}}, {"type": "Point", "id": 83, "coordinates": [169.375, 270.125], "properties": {"globaltype": "visiblePoint"}}, {"type": "Point", "id": 84, "coordinates": [178.875, 270.375], "properties": {"globaltype": "visiblePoint"}}, {"type": "Point", "id": 85, "coordinates": [190, 269.625], "properties": {"globaltype": "visiblePoint"}}, {"type": "Point", "id": 86, "coordinates": [200.625, 269.25], "properties": {"globaltype": "visiblePoint"}}, {"type": "Point", "id": 87, "coordinates": [138.75, 296.25], "properties": {"globaltype": "visiblePoint"}}, {"type": "Point", "id": 88, "coordinates": [173.75, 286.5], "properties": {"globaltype": "visiblePoint"}}, {"type": "Point", "id": 89, "coordinates": [181, 287], "properties": {"globaltype": "visiblePoint"}}, {"type": "Point", "id": 90, "coordinates": [189, 286], "properties": {"globaltype": "visiblePoint"}}, {"type": "Point", "id": 91, "coordinates": [219, 296.25], "properties": {"globaltype": "visiblePoint"}}, {"type": "Point", "id": 92, "coordinates": [182.5, 321.25], "properties": {"globaltype": "visiblePoint"}}, {"type": "Point", "id": 93, "coordinates": [155.5, 288.25], "properties": {"globaltype": "visiblePoint"}}, {"type": "Point", "id": 94, "coordinates": [206.75, 288], "properties": {"globaltype": "visiblePoint"}}, {"type": "Point", "id": 95, "coordinates": [207.25, 314.375], "properties": {"globaltype": "visiblePoint"}}, {"type": "Point", "id": 96, "coordinates": [153.5, 317.5], "properties": {"globaltype": "visiblePoint"}}, {"type": "Point", "id": 97, "coordinates": [139.75, 296.25], "properties": {"globaltype": "visiblePoint"}}, {"type": "Point", "id": 98, "coordinates": [218.25, 296.5], "properties": {"globaltype": "visiblePoint"}}, {"type": "Point", "id": 99, "coordinates": [173.75, 297.125], "properties": {"globaltype": "visiblePoint"}}, {"type": "Point", "id": 100, "coordinates": [181.5, 297.5], "properties": {"globaltype": "visiblePoint"}}, {"type": "Point", "id": 101, "coordinates": [189.75, 297.25], "properties": {"globaltype": "visiblePoint"}}, {"type": "Point", "id": 102, "coordinates": [173.625, 305.75], "properties": {"globaltype": "visiblePoint"}}, {"type": "Point", "id": 103, "coordinates": [181.875, 305.75], "properties": {"globaltype": "visiblePoint"}}, {"type": "Point", "id": 104, "coordinates": [190.25, 304.75], "properties": {"globaltype": "visiblePoint"}}, {"type": "Point", "id": 105, "coordinates": [173.5, 321.375], "properties": {"globaltype": "visiblePoint"}}, {"type": "Point", "id": 106, "coordinates": [191.125, 320.875], "properties": {"globaltype": "visiblePoint"}}], "WorkLoad": {"race": "Asian", "eye": "open", "orientation": "forward", "background": "nocolor", "gender": "female", "mouth": "open", "occlusion": "covered", "cap": "no", "age": "young", "glasses": "no"}, "Filepath": "session01\\000272.jpg"}