{"DataList": [{"type": "Point", "id": 1, "coordinates": [182.5, 467.5], "properties": {"globaltype": "visiblePoint"}}, {"type": "Point", "id": 2, "coordinates": [181, 502], "properties": {"globaltype": "visiblePoint"}}, {"type": "Point", "id": 3, "coordinates": [183, 537.5], "properties": {"globaltype": "visiblePoint"}}, {"type": "Point", "id": 4, "coordinates": [189.5, 571], "properties": {"globaltype": "visiblePoint"}}, {"type": "Point", "id": 5, "coordinates": [196.09378002144794, 605.5313667500753], "properties": {"globaltype": "visiblePoint"}}, {"type": "Point", "id": 6, "coordinates": [204, 639.25], "properties": {"globaltype": "visiblePoint"}}, {"type": "Point", "id": 7, "coordinates": [209.02632025784874, 671.1028959987838], "properties": {"globaltype": "visiblePoint"}}, {"type": "Point", "id": 8, "coordinates": [215.7502953216904, 702.7215784315501], "properties": {"globaltype": "visiblePoint"}}, {"type": "Point", "id": 9, "coordinates": [226.23107213886797, 733.3020056650735], "properties": {"globaltype": "visiblePoint"}}, {"type": "Point", "id": 10, "coordinates": [242.24087518162034, 761.2892048206369], "properties": {"globaltype": "visiblePoint"}}, {"type": "Point", "id": 11, "coordinates": [263.6093938681263, 785.4483610899248], "properties": {"globaltype": "visiblePoint"}}, {"type": "Point", "id": 12, "coordinates": [288.8843232060616, 805.4517222041674], "properties": {"globaltype": "visiblePoint"}}, {"type": "Point", "id": 13, "coordinates": [316.5256960613757, 822.2649893691358], "properties": {"globaltype": "visiblePoint"}}, {"type": "Point", "id": 14, "coordinates": [343.454298985074, 840.2152177745116], "properties": {"globaltype": "visiblePoint"}}, {"type": "Point", "id": 15, "coordinates": [370.4879503219907, 858.017167709294], "properties": {"globaltype": "visiblePoint"}}, {"type": "Point", "id": 16, "coordinates": [401.32629665996495, 867.4989444989948], "properties": {"globaltype": "visiblePoint"}}, {"type": "Point", "id": 17, "coordinates": [433.5, 869.5], "properties": {"globaltype": "visiblePoint"}}, {"type": "Point", "id": 18, "coordinates": [464.8865806194232, 863.316129043352], "properties": {"globaltype": "visiblePoint"}}, {"type": "Point", "id": 19, "coordinates": [493.6965916764392, 849.1209547956345], "properties": {"globaltype": "visiblePoint"}}, {"type": "Point", "id": 20, "coordinates": [519.9148209773592, 830.450562313861], "properties": {"globaltype": "visiblePoint"}}, {"type": "Point", "id": 21, "coordinates": [543.7921147833667, 808.8018159297475], "properties": {"globaltype": "visiblePoint"}}, {"type": "Point", "id": 22, "coordinates": [568.1299292506731, 787.6800595783806], "properties": {"globaltype": "visiblePoint"}}, {"type": "Point", "id": 23, "coordinates": [591.6345065053235, 765.708595323859], "properties": {"globaltype": "visiblePoint"}}, {"type": "Point", "id": 24, "coordinates": [612.0730712192168, 740.8949601223759], "properties": {"globaltype": "visiblePoint"}}, {"type": "Point", "id": 25, "coordinates": [626.0825519264645, 712.1881214400627], "properties": {"globaltype": "visiblePoint"}}, {"type": "Point", "id": 26, "coordinates": [634.1009592423816, 680.9762109925927], "properties": {"globaltype": "visiblePoint"}}, {"type": "Point", "id": 27, "coordinates": [638.3478065574286, 649.121009471143], "properties": {"globaltype": "visiblePoint"}}, {"type": "Point", "id": 28, "coordinates": [641, 617], "properties": {"globaltype": "visiblePoint"}}, {"type": "Point", "id": 29, "coordinates": [644.875, 580.25], "properties": {"globaltype": "visiblePoint"}}, {"type": "Point", "id": 30, "coordinates": [648.375, 543.375], "properties": {"globaltype": "visiblePoint"}}, {"type": "Point", "id": 31, "coordinates": [654.5, 507.5], "properties": {"globaltype": "inVisiblePoint"}}, {"type": "Point", "id": 32, "coordinates": [657, 472.5], "properties": {"globaltype": "inVisiblePoint"}}, {"type": "Point", "id": 33, "coordinates": [662.5, 434.5], "properties": {"globaltype": "inVisiblePoint"}}, {"type": "Point", "id": 34, "coordinates": [214.5, 501.75], "properties": {"globaltype": "visiblePoint"}}, {"type": "Point", "id": 35, "coordinates": [229, 459.75], "properties": {"globaltype": "visiblePoint"}}, {"type": "Point", "id": 36, "coordinates": [270, 438.75], "properties": {"globaltype": "visiblePoint"}}, {"type": "Point", "id": 37, "coordinates": [318.5, 440.75], "properties": {"globaltype": "visiblePoint"}}, {"type": "Point", "id": 38, "coordinates": [366.5, 451], "properties": {"globaltype": "visiblePoint"}}, {"type": "Point", "id": 39, "coordinates": [251, 495.25], "properties": {"globaltype": "visiblePoint"}}, {"type": "Point", "id": 40, "coordinates": [286.5, 482.25], "properties": {"globaltype": "visiblePoint"}}, {"type": "Point", "id": 41, "coordinates": [320, 475.75], "properties": {"globaltype": "visiblePoint"}}, {"type": "Point", "id": 42, "coordinates": [357.5, 476.75], "properties": {"globaltype": "visiblePoint"}}, {"type": "Point", "id": 43, "coordinates": [431, 451.75], "properties": {"globaltype": "visiblePoint"}}, {"type": "Point", "id": 44, "coordinates": [476.5, 429.75], "properties": {"globaltype": "visiblePoint"}}, {"type": "Point", "id": 45, "coordinates": [524.5, 420.75], "properties": {"globaltype": "visiblePoint"}}, {"type": "Point", "id": 46, "coordinates": [572, 428.25], "properties": {"globaltype": "visiblePoint"}}, {"type": "Point", "id": 47, "coordinates": [600, 461.25], "properties": {"globaltype": "visiblePoint"}}, {"type": "Point", "id": 48, "coordinates": [443.5, 476.25], "properties": {"globaltype": "visiblePoint"}}, {"type": "Point", "id": 49, "coordinates": [484.5, 469.25], "properties": {"globaltype": "visiblePoint"}}, {"type": "Point", "id": 50, "coordinates": [524.5, 470.25], "properties": {"globaltype": "visiblePoint"}}, {"type": "Point", "id": 51, "coordinates": [564.5, 479.25], "properties": {"globaltype": "visiblePoint"}}, {"type": "Point", "id": 52, "coordinates": [277.25, 531], "properties": {"globaltype": "visiblePoint"}}, {"type": "Point", "id": 53, "coordinates": [298.125, 520.375], "properties": {"globaltype": "visiblePoint"}}, {"type": "Point", "id": 54, "coordinates": [318.25, 521], "properties": {"globaltype": "visiblePoint"}}, {"type": "Point", "id": 55, "coordinates": [337.875, 537.25], "properties": {"globaltype": "visiblePoint"}}, {"type": "Point", "id": 56, "coordinates": [315.5, 542.625], "properties": {"globaltype": "visiblePoint"}}, {"type": "Point", "id": 57, "coordinates": [295, 541.125], "properties": {"globaltype": "visiblePoint"}}, {"type": "Point", "id": 58, "coordinates": [308.375, 519.125], "properties": {"globaltype": "visiblePoint"}}, {"type": "Point", "id": 59, "coordinates": [305.25, 543], "properties": {"globaltype": "visiblePoint"}}, {"type": "Point", "id": 60, "coordinates": [314.625, 530.5], "properties": {"globaltype": "visiblePoint"}}, {"type": "Point", "id": 61, "coordinates": [307.125, 534], "properties": {"globaltype": "visiblePoint"}}, {"type": "Point", "id": 62, "coordinates": [471.625, 528.375], "properties": {"globaltype": "visiblePoint"}}, {"type": "Point", "id": 63, "coordinates": [489.875, 511.75], "properties": {"globaltype": "visiblePoint"}}, {"type": "Point", "id": 64, "coordinates": [509.625, 507.875], "properties": {"globaltype": "visiblePoint"}}, {"type": "Point", "id": 65, "coordinates": [533, 515.875], "properties": {"globaltype": "visiblePoint"}}, {"type": "Point", "id": 66, "coordinates": [515.625, 527.5], "properties": {"globaltype": "visiblePoint"}}, {"type": "Point", "id": 67, "coordinates": [493.125, 530.625], "properties": {"globaltype": "visiblePoint"}}, {"type": "Point", "id": 68, "coordinates": [499.125, 508.375], "properties": {"globaltype": "visiblePoint"}}, {"type": "Point", "id": 69, "coordinates": [505.125, 530.25], "properties": {"globaltype": "visiblePoint"}}, {"type": "Point", "id": 70, "coordinates": [502.875, 518.75], "properties": {"globaltype": "visiblePoint"}}, {"type": "Point", "id": 71, "coordinates": [502.625, 522], "properties": {"globaltype": "visiblePoint"}}, {"type": "Point", "id": 72, "coordinates": [402.625, 527], "properties": {"globaltype": "visiblePoint"}}, {"type": "Point", "id": 73, "coordinates": [404.25, 570.75], "properties": {"globaltype": "visiblePoint"}}, {"type": "Point", "id": 74, "coordinates": [405.125, 610.5], "properties": {"globaltype": "visiblePoint"}}, {"type": "Point", "id": 75, "coordinates": [405.5, 650.75], "properties": {"globaltype": "visiblePoint"}}, {"type": "Point", "id": 76, "coordinates": [373.5, 535], "properties": {"globaltype": "visiblePoint"}}, {"type": "Point", "id": 77, "coordinates": [436.375, 530.875], "properties": {"globaltype": "visiblePoint"}}, {"type": "Point", "id": 78, "coordinates": [365.75, 630.75], "properties": {"globaltype": "visiblePoint"}}, {"type": "Point", "id": 79, "coordinates": [459.875, 628.875], "properties": {"globaltype": "visiblePoint"}}, {"type": "Point", "id": 80, "coordinates": [346.5, 660.75], "properties": {"globaltype": "visiblePoint"}}, {"type": "Point", "id": 81, "coordinates": [478.5, 654.25], "properties": {"globaltype": "visiblePoint"}}, {"type": "Point", "id": 82, "coordinates": [372.5, 687.5], "properties": {"globaltype": "visiblePoint"}}, {"type": "Point", "id": 83, "coordinates": [391.25, 688.25], "properties": {"globaltype": "visiblePoint"}}, {"type": "Point", "id": 84, "coordinates": [412.75, 687.5], "properties": {"globaltype": "visiblePoint"}}, {"type": "Point", "id": 85, "coordinates": [434.75, 686.25], "properties": {"globaltype": "visiblePoint"}}, {"type": "Point", "id": 86, "coordinates": [452.5, 683.25], "properties": {"globaltype": "visiblePoint"}}, {"type": "Point", "id": 87, "coordinates": [346.75, 745.75], "properties": {"globaltype": "visiblePoint"}}, {"type": "Point", "id": 88, "coordinates": [400.5, 716.375], "properties": {"globaltype": "visiblePoint"}}, {"type": "Point", "id": 89, "coordinates": [419, 721.75], "properties": {"globaltype": "visiblePoint"}}, {"type": "Point", "id": 90, "coordinates": [434.25, 713.75], "properties": {"globaltype": "visiblePoint"}}, {"type": "Point", "id": 91, "coordinates": [495.75, 737], "properties": {"globaltype": "visiblePoint"}}, {"type": "Point", "id": 92, "coordinates": [419.25, 797.75], "properties": {"globaltype": "visiblePoint"}}, {"type": "Point", "id": 93, "coordinates": [371, 728], "properties": {"globaltype": "visiblePoint"}}, {"type": "Point", "id": 94, "coordinates": [467.5, 722.25], "properties": {"globaltype": "visiblePoint"}}, {"type": "Point", "id": 95, "coordinates": [465, 779], "properties": {"globaltype": "visiblePoint"}}, {"type": "Point", "id": 96, "coordinates": [374.5, 784.75], "properties": {"globaltype": "visiblePoint"}}, {"type": "Point", "id": 97, "coordinates": [350.875, 746.375], "properties": {"globaltype": "visiblePoint"}}, {"type": "Point", "id": 98, "coordinates": [491.875, 738.625], "properties": {"globaltype": "visiblePoint"}}, {"type": "Point", "id": 99, "coordinates": [400.625, 739.75], "properties": {"globaltype": "visiblePoint"}}, {"type": "Point", "id": 100, "coordinates": [418.75, 740.125], "properties": {"globaltype": "visiblePoint"}}, {"type": "Point", "id": 101, "coordinates": [434.75, 738.125], "properties": {"globaltype": "visiblePoint"}}, {"type": "Point", "id": 102, "coordinates": [400.625, 755.25], "properties": {"globaltype": "visiblePoint"}}, {"type": "Point", "id": 103, "coordinates": [418.75, 756.5], "properties": {"globaltype": "visiblePoint"}}, {"type": "Point", "id": 104, "coordinates": [434.875, 752.25], "properties": {"globaltype": "visiblePoint"}}, {"type": "Point", "id": 105, "coordinates": [400.625, 797.25], "properties": {"globaltype": "visiblePoint"}}, {"type": "Point", "id": 106, "coordinates": [436.5, 795.25], "properties": {"globaltype": "visiblePoint"}}], "WorkLoad": {"race": "Asian", "eye": "open", "orientation": "forward", "background": "nocolor", "gender": "male", "mouth": "open", "occlusion": "covered", "cap": "no", "age": "teenager", "glasses": "no"}, "Filepath": "session01\\000858.jpg"}